dokanalyse/__init__.py
dokanalyse/http_clients/__init__.py
dokanalyse/http_clients/arcgis.py
dokanalyse/http_clients/ogc_api.py
dokanalyse/http_clients/wfs.py
dokanalyse/http_clients/wfs_request.xml.txt
dokanalyse/models/__init__.py
dokanalyse/models/analysis.py
dokanalyse/models/analysis_response.py
dokanalyse/models/arcgis_analysis.py
dokanalyse/models/empty_analysis.py
dokanalyse/models/exceptions.py
dokanalyse/models/fact_part.py
dokanalyse/models/fact_sheet.py
dokanalyse/models/metadata.py
dokanalyse/models/ogc_api_analysis.py
dokanalyse/models/quality_measurement.py
dokanalyse/models/result_status.py
dokanalyse/models/wfs_analysis.py
dokanalyse/models/config/__init__.py
dokanalyse/models/config/coverage_wfs.py
dokanalyse/models/config/dataset_config.py
dokanalyse/models/config/layer.py
dokanalyse/models/config/quality_config.py
dokanalyse/models/config/quality_indicator.py
dokanalyse/models/config/quality_indicator_type.py
dokanalyse/resources/geolett.local.json
dokanalyse/resources/no.geonorge.dokanalyse.analysisinput.v0.1.schema.json
dokanalyse/services/__init__.py
dokanalyse/services/analyses.py
dokanalyse/services/codelist.py
dokanalyse/services/config.py
dokanalyse/services/coverage.py
dokanalyse/services/dataset.py
dokanalyse/services/dok_status.py
dokanalyse/services/geolett.py
dokanalyse/services/kartkatalog.py
dokanalyse/services/municipality.py
dokanalyse/services/fact_sheet/__init__.py
dokanalyse/services/fact_sheet/area_types.py
dokanalyse/services/fact_sheet/buildings.py
dokanalyse/services/fact_sheet/roads.py
dokanalyse/services/quality/__init__.py
dokanalyse/services/quality/coverage_quality.py
dokanalyse/services/quality/dataset_quality.py
dokanalyse/services/quality/object_quality.py
dokanalyse/services/raster_result/__init__.py
dokanalyse/services/raster_result/legend.py
dokanalyse/utils/__init__.py
dokanalyse/utils/constants.py
dokanalyse/utils/correlation_id_middleware.py
dokanalyse/utils/logger.py
dokanalyse/utils/socket_io.py
dokanalyse-0.1.0.dist-info/LICENSE
dokanalyse-0.1.0.dist-info/METADATA
dokanalyse-0.1.0.dist-info/WHEEL
dokanalyse-0.1.0.dist-info/top_level.txt
dokanalyse-0.1.0.dist-info/RECORD
